setup.py
cc.utils.egg-info/PKG-INFO
cc.utils.egg-info/SOURCES.txt
cc.utils.egg-info/dependency_links.txt
cc.utils.egg-info/requires.txt
cc.utils.egg-info/top_level.txt
cc.utils.egg-info/zip-safe
cutils/__init__.py
cutils/check_list.py
cutils/create_sh.py
cutils/gmail.py
cutils/location.py
cutils/progress_bar.py
cutils/requests_util.py
cutils/split_merge.py
cutils/unique.py
cutils/update_input.py