Metadata-Version: 1.0
Name: cc.utils
Version: 0.0.14
Summary: cc personal use
Home-page: UNKNOWN
Author: cchen224
Author-email: phantomkidding@gmail.com
License: MIT License
Keywords: cchen224
Platform: any
